MANIFEST.in
README.rst
buildout.cfg
setup.cfg
setup.py
collective/__init__.py
collective.localheaderandfooter.egg-info/PKG-INFO
collective.localheaderandfooter.egg-info/SOURCES.txt
collective.localheaderandfooter.egg-info/dependency_links.txt
collective.localheaderandfooter.egg-info/entry_points.txt
collective.localheaderandfooter.egg-info/namespace_packages.txt
collective.localheaderandfooter.egg-info/not-zip-safe
collective.localheaderandfooter.egg-info/requires.txt
collective.localheaderandfooter.egg-info/top_level.txt
collective/localheaderandfooter/__init__.py
collective/localheaderandfooter/behavior.py
collective/localheaderandfooter/config.py
collective/localheaderandfooter/configure.zcml
collective/localheaderandfooter/interfaces.py
collective/localheaderandfooter/testing.py
collective/localheaderandfooter/utils.py
collective/localheaderandfooter/viewlets.py
collective/localheaderandfooter/vocabularies.py
collective/localheaderandfooter/profiles/default/browserlayer.xml
collective/localheaderandfooter/profiles/default/metadata.xml
collective/localheaderandfooter/profiles/default/registry.xml
collective/localheaderandfooter/profiles/testfixture/metadata.xml
collective/localheaderandfooter/profiles/testfixture/types.xml
collective/localheaderandfooter/profiles/testfixture/types/testdexterityct.xml
collective/localheaderandfooter/tests/__init__.py
collective/localheaderandfooter/tests/base.robot
collective/localheaderandfooter/tests/test_functional.py
collective/localheaderandfooter/tests/test_localheaderandfooter.robot
collective/localheaderandfooter/tests/test_localheaderandfooter.txt
collective/localheaderandfooter/tests/test_robot.py
collective/localheaderandfooter/tests/test_setup.py
docs/HISTORY.txt
docs/INSTALL.txt
docs/LICENSE.GPL
docs/LICENSE.txt